kerasncp/__init__.py
kerasncp/ltc_cell.py
kerasncp/utils.py
kerasncp/datasets/__init__.py
kerasncp/datasets/icra2020_lidar_collision_avoidance.py
kerasncp/paddle/__init__.py
kerasncp/paddle/ltc_cell.py
kerasncp/tf/__init__.py
kerasncp/tf/cfc_cell.py
kerasncp/tf/ltc_cell.py
kerasncp/tf/mm_rnn.py
kerasncp/torch/__init__.py
kerasncp/torch/ltc_cell.py
kerasncp/wirings/__init__.py
kerasncp/wirings/wirings.py
keras_ncp-2.1.0.dist-info/LICENSE
keras_ncp-2.1.0.dist-info/METADATA
keras_ncp-2.1.0.dist-info/WHEEL
keras_ncp-2.1.0.dist-info/top_level.txt
keras_ncp-2.1.0.dist-info/RECORD
