Metadata-Version: 2.1
Name: keras-ncp
Version: 2.1.0
Summary: Neural Circuit Policies implementation for Keras (TensorFlow 2) and PyTorch
Home-page: https://github.com/mlech26l/keras-ncp
Author: Mathias Lechner
Author-email: mlech26l@gmail.com
License: Apache License 2.0
Platform: UNKNOWN
Classifier: Programming Language :: Python
Classifier: Programming Language :: Python :: 3.6
Classifier: Operating System :: Unix
Classifier: Operating System :: Microsoft :: Windows
Classifier: Operating System :: MacOS
Classifier: Intended Audience :: Science/Research
Classifier: Topic :: Scientific/Engineering
Classifier: Topic :: Software Development
License-File: LICENSE
Requires-Dist: future
Requires-Dist: matplotlib
Requires-Dist: networkx
Requires-Dist: packaging
